egritools/__init__.py
egritools/__main__.py
egritools/change_extension.py
egritools/combine_txt.py
egritools/create_venv.py
egritools/egripad_kivy.py
egritools/egripad_tkinter.py
egritools/file_processor.py
egritools/file_processor_api.py
egritools/file_processor_chunks.py
egritools/gpt2_trainer.py
egritools/hf_upload.py
egritools/instantbackup.py
egritools/launcher_gui.py
egritools/lmstudio.py
egritools/paraphrase.py
egritools/preclean_gui.py
egritools/run_paraphrase.py
egritools/tokenizer_gui.py
egritools/wheel_manager.py
egritools/wheeldl_config.json
egritools/devtools/config_editor.py
egritools/devtools/console.py
egritools/devtools/file_editor.py
egritools/devtools/log_viewer.py
egritools/devtools/sandbox.py
egritools/selfedit/__init__.py
egritools/selfedit/editor.py
egritools-0.8.0.dist-info/entry_points.txt
egritools-0.8.0.dist-info/licenses/LICENSE
egritools-0.8.0.dist-info/WHEEL
egritools-0.8.0.dist-info/METADATA
egritools-0.8.0.dist-info/RECORD
