Metadata-Version: 2.4
Name: egritools
Version: 0.8.0
Summary: Local utility toolkit by Egrigor86
Author-email: "Christopher (Egrigor86)" <egrigor86@gmail.com>
License-File: LICENSE
